b22ao/__init__.py
b22ao/_version.py
b22ao/aosystem.py
b22ao/base.py
b22ao/log.py
b22ao/message.py
b22ao/pvs.py
b22ao-0.1.0.dist-info/LICENSE
b22ao-0.1.0.dist-info/METADATA
b22ao-0.1.0.dist-info/WHEEL
b22ao-0.1.0.dist-info/top_level.txt
b22ao-0.1.0.dist-info/RECORD
