Metadata-Version: 2.1
Name: b22ao
Version: 0.1.0
Summary: API for b22 adaptive optics operations.
Author-email: Douglas Winter <douglas.winter@diamond.ac.uk>
License: MIT License
Project-URL: GitLab, https://gitlab.diamond.ac.uk/daq/tools/b22/b22ao
Classifier: Development Status :: 3 - Alpha
Classifier: License :: OSI Approved :: MIT License
Classifier: Operating System :: OS Independent
Classifier: Programming Language :: Python :: 3.8
Classifier: Programming Language :: Python :: 3.9
Classifier: Programming Language :: Python :: 3.10
Classifier: Programming Language :: Python :: 3.11
Requires-Python: >=3.8
License-File: LICENSE
Requires-Dist: numpy
Requires-Dist: scipy
Requires-Dist: dcor
Requires-Dist: pyepics
Requires-Dist: p4p
Requires-Dist: graypy
Provides-Extra: dev
Requires-Dist: black ; extra == 'dev'
Requires-Dist: mypy ; extra == 'dev'
Requires-Dist: bump2version ; extra == 'dev'
Requires-Dist: pipdeptree ; extra == 'dev'
Requires-Dist: flake8-isort ; extra == 'dev'
Requires-Dist: pre-commit ; extra == 'dev'
Requires-Dist: pytest-cov ; extra == 'dev'
Requires-Dist: pytest-random-order ; extra == 'dev'
Requires-Dist: types-mock ; extra == 'dev'
Requires-Dist: types-requests ; extra == 'dev'
